phoenixapi/__init__.py
phoenixapi/api.py
phoenixapi/entities.py
phoenixapi/finder.py
phoenixapi/clients/__init__.py
phoenixapi/clients/base_client.py
phoenixapi/clients/bot_controller.py
phoenixapi/clients/client_socket.py
phoenixapi/clients/friend_manager.py
phoenixapi/clients/inventory_manager.py
phoenixapi/clients/login_manager.py
phoenixapi/clients/packet_manager.py
phoenixapi/clients/pet_manager.py
phoenixapi/clients/player_manager.py
phoenixapi/clients/scene_manager.py
phoenixapi/clients/skill_manager.py
phoenix_bot_api-1.0.8.dist-info/METADATA
phoenix_bot_api-1.0.8.dist-info/WHEEL
phoenix_bot_api-1.0.8.dist-info/licenses/LICENSE
phoenix_bot_api-1.0.8.dist-info/RECORD
