Metadata-Version: 2.4
Name: phoenix-bot-api
Version: 1.0.8
Summary: Python client for Phoenix API
Project-URL: GitHub, https://github.com/hatz2/PhoenixAPI
Author: Hatz
License-Expression: MIT
License-File: LICENSE
Classifier: Operating System :: OS Independent
Classifier: Programming Language :: Python :: 3
Requires-Python: >=3.11
Requires-Dist: pywin32>=311
